<Properties StartupConfiguration="{85B01A8C-30A2-3438-3984-CFDBF205CF2B}|">
  <MonoDevelop.Ide.Workbench ActiveDocument="Assets/Scripts/UIControl.cs">
    <Files>
      <File FileName="Assets/Scripts/UIControl.cs" Line="14" Column="12" />
      <File FileName="Assets/Scripts/PlayerControl.cs" Line="1" Column="1" />
    </Files>
    <Pads>
      <Pad Id="ProjectPad">
        <State name="__root__">
          <Node name="PEMDAS" expanded="True">
            <Node name="Assets" expanded="True">
              <Node name="Scripts" expanded="True">
                <Node name="UIControl.cs" selected="True" />
              </Node>
            </Node>
          </Node>
        </State>
      </Pad>
      <Pad Id="MonoDevelop.UnitTesting.TestPad">
        <State name="__root__">
          <Node name="Unity" expanded="True" selected="True" />
        </State>
      </Pad>
    </Pads>
  </MonoDevelop.Ide.Workbench>
  <MonoDevelop.Ide.DebuggingService.PinnedWatches />
  <MonoDevelop.Ide.Workspace ActiveConfiguration="Debug" />
  <MonoDevelop.Ide.ItemProperties.Assembly-CSharp PreferredExecutionTarget="26fee57e-3113-412d-a789-2872ae7d17f0" />
  <MonoDevelop.Ide.DebuggingService.Breakpoints>
    <BreakpointStore />
  </MonoDevelop.Ide.DebuggingService.Breakpoints>
  <MultiItemStartupConfigurations />
</Properties>